{
  "dashboard": {
    "id": null,
    "title": "Expense Tracker API Dashboard",
    "tags": ["expense-tracker", "api"],
    "timezone": "browser",
    "panels": [
      {
        "id": 1,
        "title": "Request Rate",
        "type": "stat",
        "targets": [
          {
            "expr": "rate(http_requests_total[5m])",
            "legendFormat": "Requests/sec"
          }
        ],
        "gridPos": {"h": 8, "w": 12, "x": 0, "y": 0}
      },
      {
        "id": 2,
        "title": "Error Rate",
        "type": "stat",
        "targets": [
          {
            "expr": "rate(http_requests_total{status_code=~\"5..\"}[5m])",
            "legendFormat": "Errors/sec"
          }
        ],
        "gridPos": {"h": 8, "w": 12, "x": 12, "y": 0}
      },
      {
        "id": 3,
        "title": "Response Time",
        "type": "graph",
        "targets": [
          {
            "expr": "histogram_quantile(0.50, rate(http_request_duration_seconds_bucket[5m]))",
            "legendFormat": "50th percentile"
          },
          {
            "expr": "histogram_quantile(0.95, rate(http_request_duration_seconds_bucket[5m]))",
            "legendFormat": "95th percentile"
          },
          {
            "expr": "histogram_quantile(0.99, rate(http_request_duration_seconds_bucket[5m]))",
            "legendFormat": "99th percentile"
          }
        ],
        "gridPos": {"h": 8, "w": 24, "x": 0, "y": 8}
      },
      {
        "id": 4,
        "title": "Database Query Rate",
        "type": "graph",
        "targets": [
          {
            "expr": "rate(database_queries_total[5m])",
            "legendFormat": "{{operation}} - {{table}}"
          }
        ],
        "gridPos": {"h": 8, "w": 12, "x": 0, "y": 16}
      },
      {
        "id": 5,
        "title": "Database Query Duration",
        "type": "graph",
        "targets": [
          {
            "expr": "histogram_quantile(0.95, rate(database_query_duration_seconds_bucket[5m]))",
            "legendFormat": "95th percentile"
          }
        ],
        "gridPos": {"h": 8, "w": 12, "x": 12, "y": 16}
      },
      {
        "id": 6,
        "title": "HTTP Status Codes",
        "type": "graph",
        "targets": [
          {
            "expr": "rate(http_requests_total[5m])",
            "legendFormat": "{{status_code}}"
          }
        ],
        "gridPos": {"h": 8, "w": 24, "x": 0, "y": 24}
      }
    ],
    "time": {
      "from": "now-1h",
      "to": "now"
    },
    "refresh": "5s"
  }
}